infercnvpy/__init__.py
infercnvpy/_util.py
infercnvpy/datasets/__init__.py
infercnvpy/datasets/data/__init__.py
infercnvpy/datasets/data/oligodendroglioma.h5ad
infercnvpy/io/__init__.py
infercnvpy/io/_genepos.py
infercnvpy/io/_scevan.py
infercnvpy/pl/__init__.py
infercnvpy/pl/_chromosome_heatmap.py
infercnvpy/pp/__init__.py
infercnvpy/tl/__init__.py
infercnvpy/tl/_copykat.py
infercnvpy/tl/_infercnv.py
infercnvpy/tl/_scores.py
infercnvpy-0.6.1.dist-info/METADATA
infercnvpy-0.6.1.dist-info/WHEEL
infercnvpy-0.6.1.dist-info/licenses/LICENSE
infercnvpy-0.6.1.dist-info/RECORD
