Metadata-Version: 2.4
Name: infercnvpy
Version: 0.6.1
Summary: Infercnv is a scalable python library to infer copy number variation (CNV) events from single cell transcriptomics data. It is heavliy inspired by InferCNV, but plays nicely with scanpy and is much more scalable.
Project-URL: Documentation, https://infercnvpy.readthedocs.io/
Project-URL: Source, https://github.com/icbi-lab/infercnvpy
Project-URL: Home-page, https://github.com/icbi-lab/infercnvpy
Author: Gregor Sturm
Maintainer-email: Gregor Sturm <gregor.sturm@i-med.ac.at>
License: BSD 3-Clause License
License-File: LICENSE
Requires-Python: >=3.10
Requires-Dist: anndata>=0.7.3
Requires-Dist: leidenalg
Requires-Dist: numpy>=1.20
Requires-Dist: pandas>=1
Requires-Dist: pybiomart>=0.2.0
Requires-Dist: pycairo>=1.20; sys_platform == 'win32'
Requires-Dist: pyreadr
Requires-Dist: pytest-benchmark
Requires-Dist: pytoml
Requires-Dist: scanpy>=1.10
Requires-Dist: session-info
Requires-Dist: tqdm>=4.63.0
Provides-Extra: copykat
Requires-Dist: rpy2; extra == 'copykat'
Provides-Extra: dev
Requires-Dist: pre-commit; extra == 'dev'
Provides-Extra: doc
Requires-Dist: docutils!=0.18.*,!=0.19.*,>=0.8; extra == 'doc'
Requires-Dist: ipykernel; extra == 'doc'
Requires-Dist: jupyter-client; extra == 'doc'
Requires-Dist: myst-nb>=1.1.0; extra == 'doc'
Requires-Dist: pandas; extra == 'doc'
Requires-Dist: pycairo; extra == 'doc'
Requires-Dist: setuptools; extra == 'doc'
Requires-Dist: sphinx-autodoc-typehints; extra == 'doc'
Requires-Dist: sphinx-book-theme>=1.0.0; extra == 'doc'
Requires-Dist: sphinx-copybutton; extra == 'doc'
Requires-Dist: sphinx>=4.2; extra == 'doc'
Requires-Dist: sphinxcontrib-bibtex>=1.0.0; extra == 'doc'
Requires-Dist: sphinxext-opengraph; extra == 'doc'
Provides-Extra: gtf
Requires-Dist: gtfparse>=2.1; extra == 'gtf'
Provides-Extra: test
Requires-Dist: coverage; extra == 'test'
Requires-Dist: openpyxl; extra == 'test'
Requires-Dist: pytest; extra == 'test'
